README.md
setup.cfg
setup.py
v2cjson/__init__.py
v2cjson/code.py
v2cjson/test.py
v2cjson.egg-info/PKG-INFO
v2cjson.egg-info/SOURCES.txt
v2cjson.egg-info/dependency_links.txt
v2cjson.egg-info/not-zip-safe
v2cjson.egg-info/requires.txt
v2cjson.egg-info/top_level.txt