Metadata-Version: 1.0
Name: v2cjson
Version: 0.2
Summary: Var 2 cool highlighted JSON
Home-page: https://github.com/57uff3r/pearsondictionary
Author: Andrey Korchak
Author-email: 57uff3r@gmail.com
License: MIT
Platform: UNKNOWN
